bachstelze/__main__.py
bachstelze-0.1.dist-info/LICENSE
bachstelze-0.1.dist-info/METADATA
bachstelze-0.1.dist-info/WHEEL
bachstelze-0.1.dist-info/entry_points.txt
bachstelze-0.1.dist-info/top_level.txt
bachstelze-0.1.dist-info/RECORD
